{
  "ok": true,
  "error": null,
  "dryRun": false,
  "consent": {
    "selector": "//button[contains(normalize-space(.),\"Consent and continue\")]",
    "dismissCheck": "detached",
    "matchCountBeforeClick": null,
    "visibleBeforeClick": true,
    "dismissedAfterMs": 1866,
    "postDismissDomHits": {
      "accept all": 0,
      "decline all": 0,
      "reject all": 0,
      "cookie": 1
    }
  },
  "capture": {
    "mhtmlKb": 6689,
    "screenshotKb": 2472,
    "beforeDismissScreenshotPath": null,
    "loadStateDegraded": null,
    "externalFontSrcCount": 0,
    "unembeddedFontUrls": [],
    "embeddedFontCount": 38,
    "mhtmlKbBeforeFontEmbed": 3860,
    "fontFetchFailures": [],
    "embeddedFamilies": [
      "Roboto",
      "Roboto Bold",
      "Roboto Condensed",
      "Roboto Condensed Bold",
      "SpiegelSans",
      "SpiegelSansUI",
      "SpiegelSerifDisplayUI",
      "SpiegelSerifUI",
      "SpiegelSlabCdUI",
      "hs-icons"
    ],
    "fontUrls": {
      "embedded": 0,
      "absolute": 18,
      "relativeResolved": 20,
      "unresolvable": []
    },
    "externalized": false,
    "externalAssetUrl": null,
    "externalAssetSha256": null,
    "removedStaleLocalMhtml": false,
    "removedStalePointer": false
  },
  "env": {
    "source": "browserbase",
    "chromiumVersion": null,
    "viewport": {
      "width": 1280,
      "height": 720
    },
    "frozenAt": "2026-06-21T21:17:38.085Z"
  },
  "failureClass": null,
  "captureValidity": {
    "ok": true,
    "textLen": 34745,
    "interactiveCount": 1003,
    "heroHasMeaningfulHeading": true,
    "challengeMarkersFound": [],
    "reason": null
  },
  "timing": {
    "gotoMs": 7085,
    "consentMs": 3194,
    "scrollMs": 5783,
    "captureMs": 45290
  }
}